lldb_rust_pretty/__init__.py
lldb_rust_pretty/logger.py
lldb_rust_pretty/py.typed
lldb_rust_pretty-0.2.0.dist-info/METADATA
lldb_rust_pretty-0.2.0.dist-info/WHEEL
lldb_rust_pretty-0.2.0.dist-info/licenses/LICENSE
lldb_rust_pretty-0.2.0.dist-info/RECORD
