Metadata-Version: 2.4
Name: lldb-rust-pretty
Version: 0.2.0
Summary: A pretty printer for Rust types in LLDB
Author-email: oneofthezombies <hunhoekim@gmail.com>
License-File: LICENSE
Requires-Python: >=3.9
